Workbook

Sheet BALANCE SHEET
A1: A2 - E FLEET OPERATIONS - REVENUE PROJECTION
A2: DESCRIPTION | B2: UNIT | C2: CY-2026 | D2: CY-2027 | E2: CY-2028 | F2: CY-2029 | G2: CY-2030 | H2: CY-2031 | I2: CY-2032 | J2: CY-2033 | K2: CY-2034 | L2: CY-2035 | M2: CY-2036 | N2: CY-2037
A3: ASSETS
A4: CURRENT ASSETS
A5: CASH & CASH EQUAVALENTS | B5: USD | C5: ='CASH FLOW'!C22 -> 61480000 | D5: ='CASH FLOW'!D22 -> 69678434 | E5: ='CASH FLOW'!E22 -> 81420140 | F5: ='CASH FLOW'!F22 -> 99464664 | G5: ='CASH FLOW'!G22 -> 1.2684962e+08 | H5: ='CASH FLOW'!H22 -> 1.6504286e+08 | I5: ='CASH FLOW'!I22 -> 2.0708283e+08 | J5: ='CASH FLOW'!J22 -> 2.1008179e+08 | ... N5: ='CASH FLOW'!N22 -> 4.5630006e+08
A6: TOTAL CURRENT ASSETS | B6: USD | C6: =C5 -> 61480000 | D6: =D5 -> 69678434 | E6: =E5 -> 81420140 | F6: =F5 -> 99464664 | G6: =G5 -> 1.2684962e+08 | H6: =H5 -> 1.6504286e+08 | I6: =I5 -> 2.0708283e+08 | J6: =J5 -> 2.1008179e+08 | ... N6: =N5 -> 4.5630006e+08
A8: NON-CURRENT ASSETS
A9: ELECTRIC TRUCKS | B9: USD | C9: ='CAPEX & DEPRECIATION'!E3 -> 0 | D9: ='CAPEX & DEPRECIATION'!F28 -> 46648000 | E9: ='CAPEX & DEPRECIATION'!G28 -> 93296000 | F9: ='CAPEX & DEPRECIATION'!H28 -> 139944000 | G9: ='CAPEX & DEPRECIATION'!I28 -> 186592000 | H9: ='CAPEX & DEPRECIATION'!J28 -> 233240000 | I9: ='CAPEX & DEPRECIATION'!K28 -> 279888000 | J9: ='CAPEX & DEPRECIATION'!L28 -> 326676000 | K9: ='CAPEX & DEPRECIATION'!M28 -> 323344000 | ... N9: ='CAPEX & DEPRECIATION'!P28 -> 313348000
A10: FLEET MANAGEMENT SOFTWARE | B10: USD | C10: ='CAPEX & DEPRECIATION'!E4 -> 0 | D10: ='CAPEX & DEPRECIATION'!F29 -> 875000 | E10: ='CAPEX & DEPRECIATION'!G29 -> 750000 | F10: ='CAPEX & DEPRECIATION'!H29 -> 625000 | G10: ='CAPEX & DEPRECIATION'!I29 -> 500000 | H10: ='CAPEX & DEPRECIATION'!J29 -> 375000 | I10: ='CAPEX & DEPRECIATION'!K29 -> 250000 | J10: ='CAPEX & DEPRECIATION'!L29 -> 125000 | K10: ='CAPEX & DEPRECIATION'!M29 -> 0 | ... N10: ='CAPEX & DEPRECIATION'!P29 -> 0
A11: HARDWARE AND OFFICE EQUIPMENT | B11: USD | C11: ='CAPEX & DEPRECIATION'!E5 -> 0 | D11: ='CAPEX & DEPRECIATION'!F30 -> 450000 | E11: ='CAPEX & DEPRECIATION'!G30 -> 400000 | F11: ='CAPEX & DEPRECIATION'!H30 -> 350000 | G11: ='CAPEX & DEPRECIATION'!I30 -> 300000 | H11: ='CAPEX & DEPRECIATION'!J30 -> 250000 | I11: ='CAPEX & DEPRECIATION'!K30 -> 200000 | J11: ='CAPEX & DEPRECIATION'!L30 -> 150000 | K11: ='CAPEX & DEPRECIATION'!M30 -> 100000 | ... N11: ='CAPEX & DEPRECIATION'!P30 -> 0
A12: TOTAL NON-CURRENT ASSETS | B12: USD | C12: =SUM(C9:C11) -> 0 | D12: =SUM(D9:D11) -> 47973000 | E12: =SUM(E9:E11) -> 94446000 | F12: =SUM(F9:F11) -> 140919000 | G12: =SUM(G9:G11) -> 187392000 | H12: =SUM(H9:H11) -> 233865000 | I12: =SUM(I9:I11) -> 280338000 | J12: =SUM(J9:J11) -> 326951000 | ... N12: =SUM(N9:N11) -> 313348000
A13: TOTAL ASSETS | B13: USD | C13: =C6+C12 -> 61480000 | D13: =D6+D12 -> 1.1765143e+08 | E13: =E6+E12 -> 1.7586614e+08 | F13: =F6+F12 -> 2.4038366e+08 | G13: =G6+G12 -> 3.1424162e+08 | H13: =H6+H12 -> 3.9890786e+08 | I13: =I6+I12 -> 4.8742083e+08 | J13: =J6+J12 -> 5.3703279e+08 | ... N13: =N6+N12 -> 7.6964806e+08
A15: LIABILITIES
A16: EQUITY | B16: USD | C16: ='SOURCE_USE OF FUNDS'!C6 -> 61480000 | D16: ='SOURCE_USE OF FUNDS'!D6 -> 116460000 | E16: ='SOURCE_USE OF FUNDS'!E6 -> 166440000 | F16: ='SOURCE_USE OF FUNDS'!F6 -> 216420000 | G16: ='SOURCE_USE OF FUNDS'!G6 -> 266400000 | H16: ='SOURCE_USE OF FUNDS'!H6 -> 316380000 | I16: ='SOURCE_USE OF FUNDS'!I6 -> 366500000 | J16: ='SOURCE_USE OF FUNDS'!J6 -> 366500000 | ... N16: ='SOURCE_USE OF FUNDS'!N6 -> 366500000
A17: RETAINED EARNINGS | B17: USD | C17: =C13-C16 -> 0 | D17: =D13-D16 -> 1191433.9 | E17: =E13-E16 -> 9426140.2 | F17: =F13-F16 -> 23963664 | G17: =G13-G16 -> 47841625 | H17: =H13-H16 -> 82527859 | I17: =I13-I16 -> 1.2092083e+08 | J17: =J13-J16 -> 1.7053279e+08 | ... N17: =N13-N16 -> 4.0314806e+08
A18: TOTAL EQUITY | C18: =C16+C17 -> 61480000 | D18: =D16+D17 -> 1.1765143e+08 | E18: =E16+E17 -> 1.7586614e+08 | F18: =F16+F17 -> 2.4038366e+08 | G18: =G16+G17 -> 3.1424162e+08 | H18: =H16+H17 -> 3.9890786e+08 | I18: =I16+I17 -> 4.8742083e+08 | J18: =J16+J17 -> 5.3703279e+08 | ... N18: =N16+N17 -> 7.6964806e+08
A19: TOTAL LIABILITIES | C19: =C18 -> 61480000 | D19: =D18 -> 1.1765143e+08 | E19: =E18 -> 1.7586614e+08 | F19: =F18 -> 2.4038366e+08 | G19: =G18 -> 3.1424162e+08 | H19: =H18 -> 3.9890786e+08 | I19: =I18 -> 4.8742083e+08 | J19: =J18 -> 5.3703279e+08 | ... N19: =N18 -> 7.6964806e+08

Sheet SOURCE_USE OF FUNDS
A1: A2 - E FLEET OPERATIONS - SOURCES & USE OF FUNDS
A3: DESCRIPTION | B3: UNIT | C3: CY-2026 | D3: CY-2027 | E3: CY-2028 | F3: CY-2029 | G3: CY-2030 | H3: CY-2031 | I3: CY-2032 | J3: CY-2033 | K3: CY-2034 | L3: CY-2035 | M3: CY-2036 | N3: CY-2037
A4: SOURCE OF FUNDS:
A5: EQUITY-INVESTOR SUBSCRIPTION (25%) | B5: USD | C5: ='ASSUMPTIONS_DATA'!D14 -> 61480000 | D5: ='ASSUMPTIONS_DATA'!E14 -> 54980000 | E5: ='ASSUMPTIONS_DATA'!F14 -> 49980000 | F5: ='ASSUMPTIONS_DATA'!G14 -> 49980000 | G5: ='ASSUMPTIONS_DATA'!H14 -> 49980000 | H5: ='ASSUMPTIONS_DATA'!I14 -> 49980000 | I5: ='ASSUMPTIONS_DATA'!J14 -> 50120000 | J5: ='ASSUMPTIONS_DATA'!K14 -> 0 | ... M5: ='ASSUMPTIONS_DATA'!N14 -> 0 | N5: 0
A6: CHANGE IN EQUITY | B6: USD | C6: =C5 -> 61480000 | D6: =D5+C6 -> 116460000 | E6: =E5+D6 -> 166440000 | F6: =F5+E6 -> 216420000 | G6: =G5+F6 -> 266400000 | H6: =H5+G6 -> 316380000 | I6: =I5+H6 -> 366500000 | J6: =J5+I6 -> 366500000 | K6: =K5+J6 -> 366500000 | ... N6: =N5+M6 -> 366500000
A8: USE OF FUNDS:
A9: ELECTRIC TRUCKS | B9: USD | C9: ='CAPEX & DEPRECIATION'!E3 -> 0 | D9: ='CAPEX & DEPRECIATION'!F3 -> 49980000 | E9: ='CAPEX & DEPRECIATION'!G3 -> 49980000 | F9: ='CAPEX & DEPRECIATION'!H3 -> 49980000 | G9: ='CAPEX & DEPRECIATION'!I3 -> 49980000 | H9: ='CAPEX & DEPRECIATION'!J3 -> 49980000 | I9: ='CAPEX & DEPRECIATION'!K3 -> 49980000 | J9: ='CAPEX & DEPRECIATION'!L3 -> 50120000 | ... N9: ='CAPEX & DEPRECIATION'!P3 -> 0
A10: FLEET MANAGEMENT SOFTWARE | B10: USD | C10: ='CAPEX & DEPRECIATION'!E4 -> 0 | D10: ='CAPEX & DEPRECIATION'!F4 -> 1000000 | E10: ='CAPEX & DEPRECIATION'!G4 -> 0 | F10: ='CAPEX & DEPRECIATION'!H4 -> 0 | G10: ='CAPEX & DEPRECIATION'!I4 -> 0 | H10: ='CAPEX & DEPRECIATION'!J4 -> 0 | I10: ='CAPEX & DEPRECIATION'!K4 -> 0 | J10: ='CAPEX & DEPRECIATION'!L4 -> 0 | ... N10: ='CAPEX & DEPRECIATION'!P4 -> 0
A11: HARDWARE AND OFFICE EQUIPMENT | B11: USD | C11: ='CAPEX & DEPRECIATION'!E5 -> 0 | D11: ='CAPEX & DEPRECIATION'!F5 -> 500000 | E11: ='CAPEX & DEPRECIATION'!G5 -> 0 | F11: ='CAPEX & DEPRECIATION'!H5 -> 0 | G11: ='CAPEX & DEPRECIATION'!I5 -> 0 | H11: ='CAPEX & DEPRECIATION'!J5 -> 0 | I11: ='CAPEX & DEPRECIATION'!K5 -> 0 | J11: ='CAPEX & DEPRECIATION'!L5 -> 0 | ... N11: ='CAPEX & DEPRECIATION'!P5 -> 0
A12: ='ASSUMPTIONS_DATA'!A12 -> OPERATING RESERVE | B12: USD | C12: 0 | D12: ='ASSUMPTIONS_DATA'!D12 -> 5000000 | E12: ='ASSUMPTIONS_DATA'!E12 -> 5000000 | F12: ='ASSUMPTIONS_DATA'!G12 -> 0 | G12: ='ASSUMPTIONS_DATA'!H12 -> 0 | H12: ='ASSUMPTIONS_DATA'!I12 -> 0 | I12: ='ASSUMPTIONS_DATA'!J12 -> 0 | J12: ='ASSUMPTIONS_DATA'!K12 -> 0 | K12: ='ASSUMPTIONS_DATA'!L12 -> 0 | L12: ='ASSUMPTIONS_DATA'!M12 -> 0 | M12: ='ASSUMPTIONS_DATA'!N12 -> 0 | N12: 0
A13: CONTINGENCY RESERVE | B13: USD | C13: 0 | D13: ='ASSUMPTIONS_DATA'!D13 -> 5000000 | E13: 0 | F13: 0 | G13: 0 | H13: 0 | I13: 0 | J13: 0 | K13: 0 | L13: 0 | M13: 0 | N13: 0
A14: TOTAL - USE OF FUNDS | B14: USD | C14: =SUM(C9:C13) -> 0 | D14: =SUM(D9:D13) -> 61480000 | E14: =SUM(E9:E13) -> 54980000 | F14: =SUM(F9:F13) -> 49980000 | G14: =SUM(G9:G13) -> 49980000 | H14: =SUM(H9:H13) -> 49980000 | I14: =SUM(I9:I13) -> 49980000 | J14: =SUM(J9:J13) -> 50120000 | ... N14: =SUM(N9:N13) -> 0

Sheet VALUATION SUMMARY
A1: A2 - E FLEET OPERATIONS - REVENUE PROJECTION
A2: METRIC | B2: UNIT | C2: CY-2028 | D2: CY-2030 | E2: CY-2033 | F2: CY-2035 | G2: CY-2036 | H2: CY-2037
A3: EBITDA | B3: USD | C3: ='INCOME STATEMENT '!E9 -> 13842866 | D3: ='INCOME STATEMENT '!G9 -> 33334373 | E3: ='INCOME STATEMENT '!J9 -> 82878011 | F3: ='INCOME STATEMENT '!L9 -> 96848512 | G3: ='INCOME STATEMENT '!M9 -> 1.0438345e+08 | H3: ='INCOME STATEMENT '!N9 -> 1.1224191e+08
A4: VALUATION MULTIPLE | C4: 2 | D4: 4 | E4: 5 | F4: 5 | G4: 8 | H4: 8
A5: ENTERPRISE VALUE | B5: USD | C5: =C3*C4 -> 27685732 | D5: =D3*D4 -> 1.3333749e+08 | E5: =E3*E4 -> 4.1439006e+08 | F5: =F3*F4 -> 4.8424256e+08 | G5: =G3*G4 -> 8.3506764e+08 | H5: =H3*H4 -> 8.9793528e+08
A6: LESS: NET DEBT | B6: USD | C6: 0 | D6: 0 | E6: 0 | F6: 0 | G6: 0 | H6: 0
A7: EQUITY VALUE | B7: USD | C7: =C5-C6 -> 27685732 | D7: =D5-D6 -> 1.3333749e+08 | E7: =E5-E6 -> 4.1439006e+08 | F7: =F5-F6 -> 4.8424256e+08 | G7: =G5-G6 -> 8.3506764e+08 | H7: =H5-H6 -> 8.9793528e+08
A8: INVESTOR 25% STAKE VALUE | B8: USD | C8: =C7*0.25 -> 6921433.1 | D8: =D7*0.25 -> 33334373 | E8: =E7*0.25 -> 1.0359751e+08 | F8: =F7*0.25 -> 1.2106064e+08 | G8: =G7*0.25 -> 2.0876691e+08 | H8: =H7*0.25 -> 2.2448382e+08
A9: MOIC | C9: =C8/'SOURCE_USE OF FUNDS'!E6 -> 0.041585154 | D9: =D8/'SOURCE_USE OF FUNDS'!G6 -> 0.12512903 | E9: =E8/'SOURCE_USE OF FUNDS'!J6 -> 0.28266716 | F9: =F8/'SOURCE_USE OF FUNDS'!L6 -> 0.33031553 | G9: =G8/'SOURCE_USE OF FUNDS'!M6 -> 0.56962322 | H9: =H8/'SOURCE_USE OF FUNDS'!N6 -> 0.61250701
A11: IRR | B11: % | G11: ='INCOME STATEMENT '!D21 -> 0.16567078

Sheet KEY METRICS
A1: A2 - E FLEET OPERATIONS - REVENUE PROJECTION
A2: DESCRIPTION | B2: UNIT | C2: CY-2027 | D2: CY-2028 | E2: CY-2029 | F2: CY-2030 | G2: CY-2031 | H2: CY-2032 | I2: CY-2033 | J2: CY-2034 | K2: CY-2035 | L2: CY-2036 | M2: CY-2037
A3: EBITDA MARGIN | B3: % | C3: ='INCOME STATEMENT '!D9/'INCOME STATEMENT '!D3 -> 0.14928262 | D3: ='INCOME STATEMENT '!E9/'INCOME STATEMENT '!E3 -> 0.18891114 | E3: ='INCOME STATEMENT '!F9/'INCOME STATEMENT '!F3 -> 0.18558718 | F3: ='INCOME STATEMENT '!G9/'INCOME STATEMENT '!G3 -> 0.19692999 | G3: ='INCOME STATEMENT '!H9/'INCOME STATEMENT '!H3 -> 0.20342633 | H3: ='INCOME STATEMENT '!I9/'INCOME STATEMENT '!I3 -> 0.207476 | I3: ='INCOME STATEMENT '!J9/'INCOME STATEMENT '!J3 -> 0.2101208 | J3: ='INCOME STATEMENT '!K9/'INCOME STATEMENT '!K3 -> 0.20667972 | ... M3: ='INCOME STATEMENT '!N9/'INCOME STATEMENT '!N3 -> 0.19436319
A4: NET MARGIN | B4: % | C4: ='INCOME STATEMENT '!D14/'INCOME STATEMENT '!D3 -> 0.034144503 | D4: ='INCOME STATEMENT '!E14/'INCOME STATEMENT '!E3 -> 0.066906364 | E4: ='INCOME STATEMENT '!F14/'INCOME STATEMENT '!F3 -> 0.06822132 | F4: ='INCOME STATEMENT '!G14/'INCOME STATEMENT '!G3 -> 0.082010677 | G4: ='INCOME STATEMENT '!H14/'INCOME STATEMENT '!H3 -> 0.091766087 | H4: ='INCOME STATEMENT '!I14/'INCOME STATEMENT '!I3 -> 0.09928354 | I4: ='INCOME STATEMENT '!J14/'INCOME STATEMENT '!J3 -> 0.10536405 | J4: ='INCOME STATEMENT '!K14/'INCOME STATEMENT '!K3 -> 0.10674807 | ... M4: ='INCOME STATEMENT '!N14/'INCOME STATEMENT '!N3 -> 0.10346328
A5: ROE | B5: % | C5: ='INCOME STATEMENT '!D14/'BALANCE SHEET'!D16 -> 0.010230413 | D5: ='INCOME STATEMENT '!E14/'BALANCE SHEET'!E16 -> 0.029456298 | E5: ='INCOME STATEMENT '!F14/'BALANCE SHEET'!F16 -> 0.036380757 | F5: ='INCOME STATEMENT '!G14/'BALANCE SHEET'!G16 -> 0.052109463 | G5: ='INCOME STATEMENT '!H14/'BALANCE SHEET'!H16 -> 0.067508167 | H5: ='INCOME STATEMENT '!I14/'BALANCE SHEET'!I16 -> 0.08322625 | I5: ='INCOME STATEMENT '!J14/'BALANCE SHEET'!J16 -> 0.11339365 | J5: ='INCOME STATEMENT '!K14/'BALANCE SHEET'!K16 -> 0.12637146 | ... L5: ='INCOME STATEMENT '!M14/'BALANCE SHEET'!M16 -> 0.15470692

Sheet ASSUMPTIONS_DATA
A1: A2 - E FLEET OPERATIONS - ASSUMPTIONS/DATA
A2: DESCRIPTION | B2: UNIT | C2: QUANTITY | D2: CY-2027 | E2: CY-2028 | F2: CY-2029 | G2: CY-2030 | H2: CY-2031 | I2: CY-2032 | J2: CY-2033 | K2: CY-2034 | L2: CY-2035 | M2: CY-2036 | N2: CY-2037
A3: NUMBER OF TRUCKS | B3: NUMBER | C3: =SUM(D3:J3) -> 5000 | D3: 714 | E3: 714 | F3: 714 | G3: 714 | H3: 714 | I3: 714 | J3: 716
A4: NUMBER OF SWAPS PER TRUCK PER DAY | B4: NUMBER | C4: 1
A5: NUMBER OF BATTERY PACKS TO SWAP PER DAY | B5: NUMBER | C5: =C3 -> 5000 | D5: =D3 -> 714 | E5: =E3 -> 714 | F5: =F3 -> 714 | G5: =G3 -> 714 | H5: =H3 -> 714 | I5: =I3 -> 714 | J5: =J3 -> 716
A6: NUMBER OF BATTERY PACKS CHARGED PER CHARGER PER DAY | B6: NUMBER | C6: 7
A8: COST PER TRUCK | B8: USD | C8: 70000
A9: TOTAL COST OF TRUCKS | B9: USD | C9: =$C$8*C3 -> 350000000 | D9: =$C$8*D3 -> 49980000 | E9: =$C$8*E3 -> 49980000 | F9: =$C$8*F3 -> 49980000 | G9: =$C$8*G3 -> 49980000 | H9: =$C$8*H3 -> 49980000 | I9: =$C$8*I3 -> 49980000 | J9: =$C$8*J3 -> 50120000
A10: FLEET MANAGEMENT SOFTWARE | B10: USD | C10: 1000000 | D10: 1000000
A11: HARDWARE AND OFFICE EQUIPMENT | B11: USD | C11: 500000 | D11: 500000
A12: OPERATING RESERVE | B12: USD | C12: 10000000 | D12: =$C$12/2 -> 5000000 | E12: =$C$12/2 -> 5000000
A13: CONTINGENCY RESERVE | B13: USD | C13: 5000000 | D13: 5000000
A14: TOTAL INVESTMENT | B14: USD | C14: =SUM(D14:J14) -> 366500000 | D14: =SUM(D9:D13) -> 61480000 | E14: =SUM(E9:E13) -> 54980000 | F14: =SUM(F9:F13) -> 49980000 | G14: =SUM(G9:G13) -> 49980000 | H14: =SUM(H9:H13) -> 49980000 | I14: =SUM(I9:I13) -> 49980000 | J14: =SUM(J9:J13) -> 50120000 | K14: =SUM(K9:K13) -> 0 | ... N14: =SUM(N9:N13) -> 0
A16: NUMBER OF TRUCKS IN OPERATION | B16: NUMBER | D16: =D3 -> 714 | E16: =E3+D16 -> 1428 | F16: =F3+E16 -> 2142 | G16: =G3+F16 -> 2856 | H16: =H3+G16 -> 3570 | I16: =I3+H16 -> 4284 | J16: =J3+I16 -> 5000 | K16: =K3+J16 -> 5000 | L16: =L3+K16 -> 5000 | ... N16: =N3+M16 -> 5000
A17: AVERAGE KILOMETRES PER TRUCK PER YEAR | B17: KM | C17: 60000
A18: TOTAL KILOMETRES OF FLEET | B18: KM | D18: =$C$17*D16 -> 42840000 | E18: =$C$17*E16 -> 85680000 | F18: =$C$17*F16 -> 128520000 | G18: =$C$17*G16 -> 171360000 | H18: =$C$17*H16 -> 214200000 | I18: =$C$17*I16 -> 257040000 | J18: =$C$17*J16 -> 300000000 | K18: =$C$17*K16 -> 300000000 | ... N18: =$C$17*N16 -> 300000000
A19: ENERGY USED PER KM | B19: KW | C19: 3
A20: TOTAL ENERGY PURCHASED | B20: KW | D20: =$C$19*D18 -> 128520000 | E20: =$C$19*E18 -> 257040000 | F20: =$C$19*F18 -> 385560000 | G20: =$C$19*G18 -> 514080000 | H20: =$C$19*H18 -> 642600000 | I20: =$C$19*I18 -> 771120000 | J20: =$C$19*J18 -> 900000000 | K20: =$C$19*K18 -> 900000000 | ... N20: =$C$19*N18 -> 900000000
A21: COST PER KW OF ENERGY | B21: USD | D21: 0.12419355 | E21: 0.1366129 | F21: 0.15027419 | G21: 0.16530161 | H21: 0.18183177 | I21: 0.20001495 | J21: 0.22001645 | K21: 0.24201809 | L21: 0.2662199 | M21: 0.29284189 | N21: 0.32212608
A22: TOTAL COST OF ENERGY | B22: USD | D22: =D21*D20 -> 15961355 | E22: =E21*E20 -> 35114981 | F22: =F21*F20 -> 57939718 | G22: =G21*G20 -> 84978253 | H22: =H21*H20 -> 1.168451e+08 | I22: =I21*I20 -> 1.5423553e+08 | J22: =J21*J20 -> 1.980148e+08 | K22: =K21*K20 -> 2.1781628e+08 | ... N22: =N21*N20 -> 2.8991347e+08
A24: NUMBER OF DAYS PER TRIP | B24: NUMBER | C24: 7
A25: NUMBER OF OPERATING DAYS IN A YEAR | B25: DAYS | C25: =365-52-10 -> 303
A26: NUMBER OF TRIPS PER YEAR PER TRUCK | B26: NUMBER | C26: =C25/C24 -> 43.285714
A27: NUMBER OF TRIPS OF FLEET PER YEAR | B27: NUMBER | D27: =D16*$C$26 -> 30906 | E27: =E16*$C$26 -> 61812 | F27: =F16*$C$26 -> 92718 | G27: =G16*$C$26 -> 123624 | H27: =H16*$C$26 -> 154530 | I27: =I16*$C$26 -> 185436 | J27: =J16*$C$26 -> 216428.57 | K27: =K16*$C$26 -> 216428.57 | ... N27: =N16*$C$26 -> 216428.57
A29: AVERAGE CHARGEABLE TONNES PER TRIP | B29: TONNES | C29: 25
A30: CHARGEABLE TONNES OF FLEET PER YEAR | B30: TONNES | D30: =$C$29*D27 -> 772650 | E30: =$C$29*E27 -> 1545300 | F30: =$C$29*F27 -> 2317950 | G30: =$C$29*G27 -> 3090600 | H30: =$C$29*H27 -> 3863250 | I30: =$C$29*I27 -> 4635900 | J30: =$C$29*J27 -> 5410714.3 | K30: =$C$29*K27 -> 5410714.3 | ... N30: =$C$29*N27 -> 5410714.3
A31: FREIGHT RATE PER TONNE | B31: ETB | C31: 7000 | D31: =C31 -> 7000 | E31: =D31*1.05 -> 7350 | F31: =E31*1.05 -> 7717.5 | G31: =F31*1.1 -> 8489.25 | H31: =G31*1.1 -> 9338.175 | I31: =H31*1.1 -> 10271.993 | J31: =I31*1.1 -> 11299.192 | K31: =J31*1.1 -> 12429.111 | L31: =K31*1.1 -> 13672.022 | M31: =L31*1.1 -> 15039.224 | N31: =M31*1.1 -> 16543.147
A32: FREIGHT RATE PER TONNE | B32: USD | C32: =C31/155 -> 45.16129 | D32: =D31/155 -> 45.16129 | E32: =E31/155 -> 47.419355 | F32: =F31/155 -> 49.790323 | G32: =G31/155 -> 54.769355 | H32: =H31/155 -> 60.24629 | I32: =I31/155 -> 66.270919 | J32: =J31/155 -> 72.898011 | ... N32: =N31/155 -> 106.72998
A33: TOTAL FREIGHT REVENUE | B33: USD | D33: =D30*D32 -> 34893871 | E33: =E30*E32 -> 73277129 | F33: =F30*F32 -> 1.1541148e+08 | G33: =G30*G32 -> 1.6927017e+08 | H33: =H30*H32 -> 2.3274648e+08 | I33: =I30*I32 -> 3.0722536e+08 | J33: =J30*J32 -> 3.9443031e+08 | K33: =K30*K32 -> 4.3387334e+08 | ... N33: =N30*N32 -> 5.7748542e+08
C35: =C32/750 -> 0.060215054

Sheet CAPEX & DEPRECIATION
A1: A2 - E FLEET OPERATIONS- CAPEX & DEPRECIATION
A2: DESCRIPTION | B2: ASSET TYPE | C2: USEFUL LIFE (YEARS) | D2: UNIT | E2: CY-2026 | F2: CY-2027 | G2: CY-2028 | H2: CY-2029 | I2: CY-2030 | J2: CY-2031 | K2: CY-2032 | L2: CY-2033 | M2: CY-2034 | N2: CY-2035 | O2: CY-2036 | P2: CY-2037
A3: ELECTRIC TRUCKS | B3: COST OF E TRUCKS WITHOUT BATTERIES | C3: 15 | D3: USD | F3: ='ASSUMPTIONS_DATA'!D9 -> 49980000 | G3: ='ASSUMPTIONS_DATA'!E9 -> 49980000 | H3: ='ASSUMPTIONS_DATA'!F9 -> 49980000 | I3: ='ASSUMPTIONS_DATA'!G9 -> 49980000 | J3: ='ASSUMPTIONS_DATA'!H9 -> 49980000 | K3: ='ASSUMPTIONS_DATA'!I9 -> 49980000 | L3: ='ASSUMPTIONS_DATA'!J9 -> 50120000 | M3: ='ASSUMPTIONS_DATA'!K9 -> 0 | ... P3: ='ASSUMPTIONS_DATA'!N9 -> 0
A4: FLEET MANAGEMENT SOFTWARE | C4: 8 | D4: USD | F4: ='ASSUMPTIONS_DATA'!D10 -> 1000000 | G4: ='ASSUMPTIONS_DATA'!E10 -> 0 | H4: ='ASSUMPTIONS_DATA'!F10 -> 0 | I4: ='ASSUMPTIONS_DATA'!G10 -> 0 | J4: ='ASSUMPTIONS_DATA'!H10 -> 0 | K4: ='ASSUMPTIONS_DATA'!I10 -> 0 | L4: ='ASSUMPTIONS_DATA'!J10 -> 0 | M4: ='ASSUMPTIONS_DATA'!K10 -> 0 | ... P4: ='ASSUMPTIONS_DATA'!N10 -> 0
A5: HARDWARE AND OFFICE EQUIPMENT | C5: 10 | D5: USD | F5: ='ASSUMPTIONS_DATA'!D11 -> 500000 | G5: ='ASSUMPTIONS_DATA'!E11 -> 0 | H5: ='ASSUMPTIONS_DATA'!F11 -> 0 | I5: ='ASSUMPTIONS_DATA'!G11 -> 0 | J5: ='ASSUMPTIONS_DATA'!H11 -> 0 | K5: ='ASSUMPTIONS_DATA'!I11 -> 0 | L5: ='ASSUMPTIONS_DATA'!J11 -> 0 | M5: ='ASSUMPTIONS_DATA'!K11 -> 0 | ... P5: ='ASSUMPTIONS_DATA'!N11 -> 0
A6: TOTAL-CAPEX | D6: USD | F6: =SUM(F3:F5) -> 51480000 | G6: =SUM(G3:G5) -> 49980000 | H6: =SUM(H3:H5) -> 49980000 | I6: =SUM(I3:I5) -> 49980000 | J6: =SUM(J3:J5) -> 49980000 | K6: =SUM(K3:K5) -> 49980000 | L6: =SUM(L3:L5) -> 50120000 | M6: =SUM(M3:M5) -> 0 | ... P6: =SUM(P3:P5) -> 0
A8: LESS: DEPRECIATION | D8: USD | E8: 0 | F8: =F24 -> 3507000 | G8: =G24 -> 6839000 | H8: =H24 -> 10171000 | I8: =I24 -> 13503000 | J8: =J24 -> 16835000 | K8: =K24 -> 20167000 | L8: =L24 -> 23508333 | M8: =M24 -> 23508333 | ... P8: =P24 -> 23333333
A9: CAPEX - CLOSING BALANCE | D9: USD | E9: =E6-E8 -> 0 | F9: =F6-F8 -> 47973000 | G9: =G6-G8 -> 43141000 | H9: =H6-H8 -> 39809000 | I9: =I6-I8 -> 36477000 | J9: =J6-J8 -> 33145000 | K9: =K6-K8 -> 29813000 | L9: =L6-L8 -> 26611667 | ... P9: =P6-P8 -> -23333333
A12: DEPRECIATION GRID
A13: DESCRIPTION | B13: YEAR OF ADDITION | C13: USEFUL LIFE (YEARS) | D13: UNIT | E13: CY-2026 | F13: CY-2027 | G13: CY-2028 | H13: CY-2029 | I13: CY-2030 | J13: CY-2031 | K13: CY-2032 | L13: CY-2033 | M13: CY-2034 | N13: CY-2035 | O13: CY-2036 | P13: CY-2037
A14: ELECTRIC TRUCKS | B14: =E13 -> CY-2026 | C14: =$C$3 -> 15 | D14: USD | F14: =$F$3/$C$14 -> 3332000 | G14: =$F$3/$C$14 -> 3332000 | H14: =$F$3/$C$14 -> 3332000 | I14: =$F$3/$C$14 -> 3332000 | J14: =$F$3/$C$14 -> 3332000 | K14: =$F$3/$C$14 -> 3332000 | L14: =$F$3/$C$14 -> 3332000 | M14: =$F$3/$C$14 -> 3332000 | ... P14: =$F$3/$C$14 -> 3332000
A15: ADDITION 1 | B15: =F13 -> CY-2027 | C15: =$C$3 -> 15 | D15: USD | G15: =$G$3/$C$15 -> 3332000 | H15: =$G$3/$C$15 -> 3332000 | I15: =$G$3/$C$15 -> 3332000 | J15: =$G$3/$C$15 -> 3332000 | K15: =$G$3/$C$15 -> 3332000 | L15: =$G$3/$C$15 -> 3332000 | M15: =$G$3/$C$15 -> 3332000 | N15: =$G$3/$C$15 -> 3332000 | ... P15: =$G$3/$C$15 -> 3332000
A16: ADDITION 2 | B16: =G13 -> CY-2028 | C16: =$C$3 -> 15 | D16: USD | H16: =$H$3/$C$16 -> 3332000 | I16: =$H$3/$C$16 -> 3332000 | J16: =$H$3/$C$16 -> 3332000 | K16: =$H$3/$C$16 -> 3332000 | L16: =$H$3/$C$16 -> 3332000 | M16: =$H$3/$C$16 -> 3332000 | N16: =$H$3/$C$16 -> 3332000 | O16: =$H$3/$C$16 -> 3332000 | P16: =$H$3/$C$16 -> 3332000
A17: ADDITION 3 | B17: =H13 -> CY-2029 | C17: =$C$3 -> 15 | D17: USD | I17: =$I$3/$C$17 -> 3332000 | J17: =$I$3/$C$17 -> 3332000 | K17: =$I$3/$C$17 -> 3332000 | L17: =$I$3/$C$17 -> 3332000 | M17: =$I$3/$C$17 -> 3332000 | N17: =$I$3/$C$17 -> 3332000 | O17: =$I$3/$C$17 -> 3332000 | P17: =$I$3/$C$17 -> 3332000
A18: ADDITION 4 | B18: =I13 -> CY-2030 | C18: =$C$3 -> 15 | D18: USD | J18: =$J$3/$C$18 -> 3332000 | K18: =$J$3/$C$18 -> 3332000 | L18: =$J$3/$C$18 -> 3332000 | M18: =$J$3/$C$18 -> 3332000 | N18: =$J$3/$C$18 -> 3332000 | O18: =$J$3/$C$18 -> 3332000 | P18: =$J$3/$C$18 -> 3332000
A19: ADDITION 5 | B19: =J13 -> CY-2031 | C19: =$C$3 -> 15 | D19: USD | K19: =$K$3/$C$19 -> 3332000 | L19: =$K$3/$C$19 -> 3332000 | M19: =$K$3/$C$19 -> 3332000 | N19: =$K$3/$C$19 -> 3332000 | O19: =$K$3/$C$19 -> 3332000 | P19: =$K$3/$C$19 -> 3332000
A20: ADDITION 6 | B20: =K13 -> CY-2032 | C20: =$C$3 -> 15 | D20: USD | L20: =$L$3/$C$20 -> 3341333.3 | M20: =$L$3/$C$20 -> 3341333.3 | N20: =$L$3/$C$20 -> 3341333.3 | O20: =$L$3/$C$20 -> 3341333.3 | P20: =$L$3/$C$20 -> 3341333.3
A21: TOTAL | F21: =SUM(F14:F20) -> 3332000 | G21: =SUM(G14:G20) -> 6664000 | H21: =SUM(H14:H20) -> 9996000 | I21: =SUM(I14:I20) -> 13328000 | J21: =SUM(J14:J20) -> 16660000 | K21: =SUM(K14:K20) -> 19992000 | L21: =SUM(L14:L20) -> 23333333 | M21: =SUM(M14:M20) -> 23333333 | ... P21: =SUM(P14:P20) -> 23333333
A22: SOFTWARE & PLATFORM DEVELOPMENT | B22: =E13 -> CY-2026 | C22: =C4 -> 8 | D22: USD | F22: =$F$4/$C$22 -> 125000 | G22: =$F$4/$C$22 -> 125000 | H22: =$F$4/$C$22 -> 125000 | I22: =$F$4/$C$22 -> 125000 | J22: =$F$4/$C$22 -> 125000 | K22: =$F$4/$C$22 -> 125000 | L22: =$F$4/$C$22 -> 125000 | M22: =$F$4/$C$22 -> 125000
A23: HARDWARE & OFFICE EQUIPMENT | B23: CY-2026 | C23: =C5 -> 10 | D23: USD | F23: =$F$5/$C$23 -> 50000 | G23: =$F$5/$C$23 -> 50000 | H23: =$F$5/$C$23 -> 50000 | I23: =$F$5/$C$23 -> 50000 | J23: =$F$5/$C$23 -> 50000 | K23: =$F$5/$C$23 -> 50000 | L23: =$F$5/$C$23 -> 50000 | M23: =$F$5/$C$23 -> 50000 | ... O23: =$F$5/$C$23 -> 50000
A24: TOTAL DEPRECIATION | F24: =F23+F22+F21 -> 3507000 | G24: =G23+G22+G21 -> 6839000 | H24: =H23+H22+H21 -> 10171000 | I24: =I23+I22+I21 -> 13503000 | J24: =J23+J22+J21 -> 16835000 | K24: =K23+K22+K21 -> 20167000 | L24: =L23+L22+L21 -> 23508333 | M24: =M23+M22+M21 -> 23508333 | ... P24: =P23+P22+P21 -> 23333333
A27: ASSET VALUE
A28: ELECTRIC TRUCKS | F28: =F3-F21 -> 46648000 | G28: =(F28-G14)+G3 -> 93296000 | H28: =(G28-H14)+H3 -> 139944000 | I28: =(H28-I14)+I3 -> 186592000 | J28: =(I28-J14)+J3 -> 233240000 | K28: =(J28-K14)+K3 -> 279888000 | L28: =(K28-L14)+L3 -> 326676000 | M28: =(L28-M14)+M3 -> 323344000 | N28: =(M28-N14)+N3 -> 320012000 | ... P28: =(O28-P14)+P3 -> 313348000
A29: SOFTWARE & PLATFORM DEVELOPMENT | F29: =F4-F22 -> 875000 | G29: =F29-G22 -> 750000 | H29: =G29-H22 -> 625000 | I29: =H29-I22 -> 500000 | J29: =I29-J22 -> 375000 | K29: =J29-K22 -> 250000 | L29: =K29-L22 -> 125000 | M29: =L29-M22 -> 0 | N29: =M29-N22 -> 0 | ... P29: =O29-P22 -> 0
A30: HARDWARE & OFFICE EQUIPMENT | F30: =F5-F23 -> 450000 | G30: =F30-G23 -> 400000 | H30: =G30-H23 -> 350000 | I30: =H30-I23 -> 300000 | J30: =I30-J23 -> 250000 | K30: =J30-K23 -> 200000 | L30: =K30-L23 -> 150000 | M30: =L30-M23 -> 100000 | N30: =M30-N23 -> 50000 | ... P30: =O30-P23 -> 0

Sheet REVENUE PROJECTION
A1: A2 - E FLEET OPERATIONS - REVENUE PROJECTION
A2: DESCRIPTION | B2: UNIT | C2: CY-2027 | D2: CY-2028 | E2: CY-2029 | F2: CY-2030 | G2: CY-2031 | H2: CY-2032 | I2: CY-2033 | J2: CY-2034 | K2: CY-2035 | L2: CY-2036 | M2: CY-2037
A3: CHARGEABLE TONNES OF FREIGHT | B3: TONNES | C3: ='ASSUMPTIONS_DATA'!D30 -> 772650 | D3: ='ASSUMPTIONS_DATA'!E30 -> 1545300 | E3: ='ASSUMPTIONS_DATA'!F30 -> 2317950 | F3: ='ASSUMPTIONS_DATA'!G30 -> 3090600 | G3: ='ASSUMPTIONS_DATA'!H30 -> 3863250 | H3: ='ASSUMPTIONS_DATA'!I30 -> 4635900 | I3: ='ASSUMPTIONS_DATA'!J30 -> 5410714.3 | J3: ='ASSUMPTIONS_DATA'!K30 -> 5410714.3 | ... M3: ='ASSUMPTIONS_DATA'!N30 -> 5410714.3
A4: RATE PER TONNE | B4: USD | C4: ='ASSUMPTIONS_DATA'!D32 -> 45.16129 | D4: ='ASSUMPTIONS_DATA'!E32 -> 47.419355 | E4: ='ASSUMPTIONS_DATA'!F32 -> 49.790323 | F4: ='ASSUMPTIONS_DATA'!G32 -> 54.769355 | G4: ='ASSUMPTIONS_DATA'!H32 -> 60.24629 | H4: ='ASSUMPTIONS_DATA'!I32 -> 66.270919 | I4: ='ASSUMPTIONS_DATA'!J32 -> 72.898011 | J4: ='ASSUMPTIONS_DATA'!K32 -> 80.187812 | ... M4: ='ASSUMPTIONS_DATA'!N32 -> 106.72998
A5: REVENUE FROM FREIGHT CHARGES | B5: USD | C5: =C3*C4 -> 34893871 | D5: =D3*D4 -> 73277129 | E5: =E3*E4 -> 1.1541148e+08 | F5: =F3*F4 -> 1.6927017e+08 | G5: =G3*G4 -> 2.3274648e+08 | H5: =H3*H4 -> 3.0722536e+08 | I5: =I3*I4 -> 3.9443031e+08 | J5: =J3*J4 -> 4.3387334e+08 | ... M5: =M3*M4 -> 5.7748542e+08

Sheet INCOME STATEMENT 
A1: A2 - E FLEET OPERATIONS - REVENUE PROJECTION
A2: DESCRIPTION | B2: UNIT | C2: CY-2026 | D2: CY-2027 | E2: CY-2028 | F2: CY-2029 | G2: CY-2030 | H2: CY-2031 | I2: CY-2032 | J2: CY-2033 | K2: CY-2034 | L2: CY-2035 | M2: CY-2036 | N2: CY-2037
A3: REVENUE | B3: USD | C3: 0 | D3: ='REVENUE PROJECTION'!C5 -> 34893871 | E3: ='REVENUE PROJECTION'!D5 -> 73277129 | F3: ='REVENUE PROJECTION'!E5 -> 1.1541148e+08 | G3: ='REVENUE PROJECTION'!F5 -> 1.6927017e+08 | H3: ='REVENUE PROJECTION'!G5 -> 2.3274648e+08 | I3: ='REVENUE PROJECTION'!H5 -> 3.0722536e+08 | J3: ='REVENUE PROJECTION'!I5 -> 3.9443031e+08 | K3: ='REVENUE PROJECTION'!J5 -> 4.3387334e+08 | ... N3: ='REVENUE PROJECTION'!M5 -> 5.7748542e+08
A4: LESS: COST OF BATTERY CHARGE | B4: USD | C4: 0 | D4: ='ASSUMPTIONS_DATA'!D22 -> 15961355 | E4: ='ASSUMPTIONS_DATA'!E22 -> 35114981 | F4: ='ASSUMPTIONS_DATA'!F22 -> 57939718 | G4: ='ASSUMPTIONS_DATA'!G22 -> 84978253 | H4: ='ASSUMPTIONS_DATA'!H22 -> 1.168451e+08 | I4: ='ASSUMPTIONS_DATA'!I22 -> 1.5423553e+08 | J4: ='ASSUMPTIONS_DATA'!J22 -> 1.980148e+08 | K4: ='ASSUMPTIONS_DATA'!K22 -> 2.1781628e+08 | ... N4: ='ASSUMPTIONS_DATA'!N22 -> 2.8991347e+08
A5: GROSS MARGIN | B5: USD | C5: =C3-C4 -> 0 | D5: =D3-D4 -> 18932516 | E5: =E3-E4 -> 38162148 | F5: =F3-F4 -> 57471760 | G5: =G3-G4 -> 84291915 | H5: =H3-H4 -> 1.1590138e+08 | I5: =I3-I4 -> 1.5298983e+08 | J5: =J3-J4 -> 1.9641551e+08 | ... N5: =N3-N4 -> 2.8757195e+08
A7: LESS: OPERATING EXPENSES | B7: USD | C7: 0 | D7: 5000000 | E7: =D7*1.2 -> 6000000 | F7: =E7*1.2 -> 7200000 | G7: =F7*1.2 -> 8640000 | H7: =G7*1.2 -> 10368000 | I7: =H7*1.2 -> 12441600 | J7: =I7*1.2 -> 14929920 | K7: =J7*1.2 -> 17915904 | L7: =K7*1.2 -> 21499085 | ... N7: =M7*1.2 -> 30958682
A8: LESS: VARIABLE OPEX (25% OF REVENUE) | B8: USD | C8: =C3*C7 -> 0 | D8: =D3*0.25 -> 8723467.7 | E8: =E3*0.25 -> 18319282 | F8: =F3*0.25 -> 28852870 | G8: =G3*0.25 -> 42317542 | H8: =H3*0.25 -> 58186620 | I8: =I3*0.25 -> 76806339 | J8: =J3*0.25 -> 98607578 | K8: =K3*0.25 -> 1.0846834e+08 | ... N8: =N3*0.25 -> 1.4437135e+08
A9: EBITDA | B9: USD | C9: =C5-C7-C8 -> 0 | D9: =D5-D7-D8 -> 5209048.4 | E9: =E5-E7-E8 -> 13842866 | F9: =F5-F7-F8 -> 21418891 | G9: =G5-G7-G8 -> 33334373 | H9: =H5-H7-H8 -> 47346763 | I9: =I5-I7-I8 -> 63741887 | J9: =J5-J7-J8 -> 82878011 | ... N9: =N5-N7-N8 -> 1.1224191e+08
A10: DEPRECIATION | B10: USD | C10: ='CAPEX & DEPRECIATION'!E8 -> 0 | D10: ='CAPEX & DEPRECIATION'!F8 -> 3507000 | E10: ='CAPEX & DEPRECIATION'!G8 -> 6839000 | F10: ='CAPEX & DEPRECIATION'!H8 -> 10171000 | G10: ='CAPEX & DEPRECIATION'!I8 -> 13503000 | H10: ='CAPEX & DEPRECIATION'!J8 -> 16835000 | I10: ='CAPEX & DEPRECIATION'!K8 -> 20167000 | J10: ='CAPEX & DEPRECIATION'!L8 -> 23508333 | ... N10: ='CAPEX & DEPRECIATION'!P8 -> 23333333
A11: EBT | B11: USD | C11: =C9-C10 -> 0 | D11: =D9-D10 -> 1702048.4 | E11: =E9-E10 -> 7003866.1 | F11: =F9-F10 -> 11247891 | G11: =G9-G10 -> 19831373 | H11: =H9-H10 -> 30511763 | I11: =I9-I10 -> 43574887 | J11: =J9-J10 -> 59369678 | ... N11: =N9-N10 -> 88908577
A12: TAX @ 30% | B12: USD | C12: 0 | D12: =D11*0.3 -> 510614.52 | E12: =E11*0.3 -> 2101159.8 | F12: =F11*0.3 -> 3374367.2 | G12: =G11*0.3 -> 5949411.9 | H12: =H11*0.3 -> 9153528.8 | I12: =I11*0.3 -> 13072466 | J12: =J11*0.3 -> 17810903 | K12: =K11*0.3 -> 19849346 | ... M12: =M11*0.3 -> 24300036 | N12: =M12*1.2 -> 29160044
A14: EAT (NET INCOME) | B14: USD | C14: =C11-C12 -> 0 | D14: =D11-D12 -> 1191433.9 | E14: =E11-E12 -> 4902706.3 | F14: =F11-F12 -> 7873523.4 | G14: =G11-G12 -> 13881961 | H14: =H11-H12 -> 21358234 | I14: =I11-I12 -> 30502421 | J14: =J11-J12 -> 41558775 | ... N14: =N11-N12 -> 59748533
A17: CUMULATIVE EAT | B17: USD | D17: =D14 -> 1191433.9 | E17: =D17+E14 -> 6094140.2 | F17: =E17+F14 -> 13967664 | G17: =F17+G14 -> 27849625 | H17: =G17+H14 -> 49207859 | I17: =H17+I14 -> 79710279 | J17: =I17+J14 -> 1.2126905e+08 | K17: =J17+K14 -> 1.6758419e+08 | L17: =K17+L14 -> 2.1900982e+08 | ... N17: =M17+N14 -> 3.3545844e+08
A18: RATE OF RETURN | B18: % | D18: =D14/'SOURCE_USE OF FUNDS'!D6 -> 0.010230413 | E18: =E14/'SOURCE_USE OF FUNDS'!E6 -> 0.029456298 | F18: =F14/'SOURCE_USE OF FUNDS'!F6 -> 0.036380757 | G18: =G14/'SOURCE_USE OF FUNDS'!G6 -> 0.052109463 | H18: =H14/'SOURCE_USE OF FUNDS'!H6 -> 0.067508167 | I18: =I14/'SOURCE_USE OF FUNDS'!I6 -> 0.08322625 | J18: =J14/'SOURCE_USE OF FUNDS'!J6 -> 0.11339365 | K18: =K14/'SOURCE_USE OF FUNDS'!K6 -> 0.12637146 | ... N18: =N14/'SOURCE_USE OF FUNDS'!N6 -> 0.16302465 | O18: EXIT VALUE
A19: INVESTOR EAT (NET INCOME) 25% | B19: USD | C19: =('SOURCE_USE OF FUNDS'!C6*-1)+C14 -> -61480000 | D19: =D14*0.25 -> 297858.47 | E19: =E14*0.25 -> 1225676.6 | F19: =F14*0.25 -> 1968380.9 | G19: =G14*0.25 -> 3470490.3 | H19: =H14*0.25 -> 5339558.5 | I19: =I14*0.25 -> 7625605.2 | J19: =J14*0.25 -> 10389694 | K19: =K14*0.25 -> 11578785 | ... N19: =N14*0.25 -> 14937133 | O19: ='VALUATION SUMMARY'!H8 -> 2.2448382e+08
A20: INVESTOR RATE OF RETURN 25% | B20: % | D20: =(D14*0.25)/'SOURCE_USE OF FUNDS'!D6 -> 0.0025576032 | E20: =(E14*0.25)/'SOURCE_USE OF FUNDS'!E6 -> 0.0073640746 | F20: =(F14*0.25)/'SOURCE_USE OF FUNDS'!F6 -> 0.0090951892 | G20: =(G14*0.25)/'SOURCE_USE OF FUNDS'!G6 -> 0.013027366 | H20: =(H14*0.25)/'SOURCE_USE OF FUNDS'!H6 -> 0.016877042 | I20: =(I14*0.25)/'SOURCE_USE OF FUNDS'!I6 -> 0.020806563 | J20: =(J14*0.25)/'SOURCE_USE OF FUNDS'!J6 -> 0.028348414 | K20: =(K14*0.25)/'SOURCE_USE OF FUNDS'!K6 -> 0.031592866 | ... N20: =(N14*0.25)/'SOURCE_USE OF FUNDS'!N6 -> 0.040756162
A21: IRR | B21: % | D21: =IRR(C19:O19,0.1) -> 0.16567078

Sheet CASH FLOW
A1: A2 - E FLEET OPERATIONS - REVENUE PROJECTION
A2: DESCRIPTION | B2: UNIT | C2: CY-2026 | D2: CY-2027 | E2: CY-2028 | F2: CY-2029 | G2: CY-2030 | H2: CY-2031 | I2: CY-2032 | J2: CY-2033 | K2: CY-2034 | L2: CY-2035 | M2: CY-2036 | N2: CY-2037
A3: OPERATING ACTIVITIES
A4: NET INCOME | B4: USD | C4: ='INCOME STATEMENT '!C14 -> 0 | D4: ='INCOME STATEMENT '!D14 -> 1191433.9 | E4: ='INCOME STATEMENT '!E14 -> 4902706.3 | F4: ='INCOME STATEMENT '!F14 -> 7873523.4 | G4: ='INCOME STATEMENT '!G14 -> 13881961 | H4: ='INCOME STATEMENT '!H14 -> 21358234 | I4: ='INCOME STATEMENT '!I14 -> 30502421 | J4: ='INCOME STATEMENT '!J14 -> 41558775 | ... N4: ='INCOME STATEMENT '!N14 -> 59748533
A5: ADD: DEPRECIATION | B5: USD | C5: ='CAPEX & DEPRECIATION'!E8 -> 0 | D5: ='CAPEX & DEPRECIATION'!F8 -> 3507000 | E5: ='CAPEX & DEPRECIATION'!G8 -> 6839000 | F5: ='CAPEX & DEPRECIATION'!H8 -> 10171000 | G5: ='CAPEX & DEPRECIATION'!I8 -> 13503000 | H5: ='CAPEX & DEPRECIATION'!J8 -> 16835000 | I5: ='CAPEX & DEPRECIATION'!K8 -> 20167000 | J5: ='CAPEX & DEPRECIATION'!L8 -> 23508333 | ... N5: ='CAPEX & DEPRECIATION'!P8 -> 23333333
A6: NET CASH FROM OPERATIONS | B6: USD | C6: =C4+C5 -> 0 | D6: =D4+D5 -> 4698433.9 | E6: =E4+E5 -> 11741706 | F6: =F4+F5 -> 18044523 | G6: =G4+G5 -> 27384961 | H6: =H4+H5 -> 38193234 | I6: =I4+I5 -> 50669421 | J6: =J4+J5 -> 65067108 | ... N6: =N4+N5 -> 83081866
A8: INVESTING ACTIVITIES
A9: CAPEX | B9: USD | C9: ='CAPEX & DEPRECIATION'!E6*-1 -> 0 | D9: ='CAPEX & DEPRECIATION'!F6*-1 -> -51480000 | E9: ='CAPEX & DEPRECIATION'!G6*-1 -> -49980000 | F9: ='CAPEX & DEPRECIATION'!H6*-1 -> -49980000 | G9: ='CAPEX & DEPRECIATION'!I6*-1 -> -49980000 | H9: ='CAPEX & DEPRECIATION'!J6*-1 -> -49980000 | I9: ='CAPEX & DEPRECIATION'!K6*-1 -> -49980000 | J9: ='CAPEX & DEPRECIATION'!L6*-1 -> -50120000 | ... N9: ='CAPEX & DEPRECIATION'!P6*-1 -> 0
A10: NET CASH FROM INVESTING | B10: USD | C10: =SUM(C9) -> 0 | D10: =SUM(D9) -> -51480000 | E10: =SUM(E9) -> -49980000 | F10: =SUM(F9) -> -49980000 | G10: =SUM(G9) -> -49980000 | H10: =SUM(H9) -> -49980000 | I10: =SUM(I9) -> -49980000 | J10: =SUM(J9) -> -50120000 | ... N10: =SUM(N9) -> 0
A12: FINANCING ACTIVITIES
A13: EQUITY INJECTION | B13: USD | C13: ='SOURCE_USE OF FUNDS'!C5 -> 61480000 | D13: ='SOURCE_USE OF FUNDS'!D5 -> 54980000 | E13: ='SOURCE_USE OF FUNDS'!E5 -> 49980000 | F13: ='SOURCE_USE OF FUNDS'!F5 -> 49980000 | G13: ='SOURCE_USE OF FUNDS'!G5 -> 49980000 | H13: ='SOURCE_USE OF FUNDS'!H5 -> 49980000 | I13: ='SOURCE_USE OF FUNDS'!I5 -> 50120000 | J13: ='SOURCE_USE OF FUNDS'!J5 -> 0 | ... N13: ='SOURCE_USE OF FUNDS'!N5 -> 0
A14: DIVIDEND | B14: % | C14: 0 | D14: 0 | E14: 0 | F14: 0 | G14: 0 | H14: 0 | I14: 0.25 | J14: 0.25 | K14: 0.25 | L14: 0.25 | M14: 0.25 | N14: 0.25
A15: DIVIDEND | B15: USD | C15: =(C4*C14)*-1 -> 0 | D15: =(D4*D14)*-1 -> 0 | E15: =(E4*E14)*-1 -> 0 | F15: =(F4*F14)*-1 -> 0 | G15: =(G4*G14)*-1 -> 0 | H15: =(H4*H14)*-1 -> 0 | I15: =(I4*I14)*-1 -> -7625605.2 | J15: =(J4*J14)*-1 -> -10389694 | ... N15: =(N4*N14)*-1 -> -14937133
A16: DIVIDEND TAX @ 15% | B16: USD | C16: =C15*0.15 -> 0 | D16: =D15*0.15 -> 0 | E16: =E15*0.15 -> 0 | F16: =F15*0.15 -> 0 | G16: =G15*0.15 -> 0 | H16: =H15*0.15 -> 0 | I16: =I15*0.15 -> -1143840.8 | J16: =J15*0.15 -> -1558454 | ... N16: =N15*0.15 -> -2240570
A17: NET CASH FROM FINANCING | B17: USD | C17: =SUM(C15:C16)+C13 -> 61480000 | D17: =SUM(D15:D16)+D13 -> 54980000 | E17: =SUM(E15:E16)+E13 -> 49980000 | F17: =SUM(F15:F16)+F13 -> 49980000 | G17: =SUM(G15:G16)+G13 -> 49980000 | H17: =SUM(H15:H16)+H13 -> 49980000 | I17: =SUM(I15:I16)+I13 -> 41350554 | J17: =SUM(J15:J16)+J13 -> -11948148 | ... N17: =SUM(N15:N16)+N13 -> -17177703
A19: NET CHANGE IN CASH | B19: USD | C19: =C17+C10+C6 -> 61480000 | D19: =D17+D10+D6 -> 8198433.9 | E19: =E17+E10+E6 -> 11741706 | F19: =F17+F10+F6 -> 18044523 | G19: =G17+G10+G6 -> 27384961 | H19: =H17+H10+H6 -> 38193234 | I19: =I17+I10+I6 -> 42039975 | J19: =J17+J10+J6 -> 2998960.2 | ... N19: =N17+N10+N6 -> 65904163
A21: CASH-OPENING BALANCE | B21: USD | C21: 0 | D21: =C22 -> 61480000 | E21: =D22 -> 69678434 | F21: =E22 -> 81420140 | G21: =F22 -> 99464664 | H21: =G22 -> 1.2684962e+08 | I21: =H22 -> 1.6504286e+08 | J21: =I22 -> 2.0708283e+08 | K21: =J22 -> 2.1008179e+08 | ... N21: =M22 -> 3.903959e+08
A22: CASH-CLOSING BALANCE | B22: USD | C22: =C17+C10+C6 -> 61480000 | D22: =D19+D21 -> 69678434 | E22: =E19+E21 -> 81420140 | F22: =F19+F21 -> 99464664 | G22: =G19+G21 -> 1.2684962e+08 | H22: =H19+H21 -> 1.6504286e+08 | I22: =I19+I21 -> 2.0708283e+08 | J22: =J19+J21 -> 2.1008179e+08 | K22: =K19+K21 -> 2.6658966e+08 | ... N22: =N19+N21 -> 4.5630006e+08
